scene_renderer/__init__.py
scene_renderer/scene_renderer.py
scene_renderer/assets/env.exr
scene_renderer-0.1.1.dist-info/METADATA
scene_renderer-0.1.1.dist-info/WHEEL
scene_renderer-0.1.1.dist-info/top_level.txt
scene_renderer-0.1.1.dist-info/RECORD
