Metadata-Version: 2.1
Name: scene_renderer
Version: 0.1.1
Summary: A Scene Renderer
Home-page: https://github.com/KunalMGupta/scene_renderer.git
Author: Kunal Gupta
Author-email: k5upta@ucsd.edu
Classifier: Programming Language :: Python :: 3
Classifier: License :: OSI Approved :: MIT License
Classifier: Operating System :: OS Independent
Requires-Python: >=3.9
